odoo/addons/ssi_l10n_id_taxform_bukti_potong_pph_f113308/README.rst
odoo/addons/ssi_l10n_id_taxform_bukti_potong_pph_f113308/__init__.py
odoo/addons/ssi_l10n_id_taxform_bukti_potong_pph_f113308/__manifest__.py
odoo/addons/ssi_l10n_id_taxform_bukti_potong_pph_f113308/data/account_journal_data.xml
odoo/addons/ssi_l10n_id_taxform_bukti_potong_pph_f113308/data/approval_template_data.xml
odoo/addons/ssi_l10n_id_taxform_bukti_potong_pph_f113308/data/ir_sequence_data.xml
odoo/addons/ssi_l10n_id_taxform_bukti_potong_pph_f113308/data/l10n_id_bukti_potong_type.xml
odoo/addons/ssi_l10n_id_taxform_bukti_potong_pph_f113308/data/policy_template_data.xml
odoo/addons/ssi_l10n_id_taxform_bukti_potong_pph_f113308/data/sequence_template_data.xml
odoo/addons/ssi_l10n_id_taxform_bukti_potong_pph_f113308/demo/account_account_demo.xml
odoo/addons/ssi_l10n_id_taxform_bukti_potong_pph_f113308/demo/account_journal_demo.xml
odoo/addons/ssi_l10n_id_taxform_bukti_potong_pph_f113308/demo/account_tax_demo.xml
odoo/addons/ssi_l10n_id_taxform_bukti_potong_pph_f113308/demo/l10n_id_bukti_potong_type_demo.xml
odoo/addons/ssi_l10n_id_taxform_bukti_potong_pph_f113308/models/__init__.py
odoo/addons/ssi_l10n_id_taxform_bukti_potong_pph_f113308/models/bukti_potong_pph_f113308_in.py
odoo/addons/ssi_l10n_id_taxform_bukti_potong_pph_f113308/models/bukti_potong_pph_f113308_in_line.py
odoo/addons/ssi_l10n_id_taxform_bukti_potong_pph_f113308/models/bukti_potong_pph_f113308_out.py
odoo/addons/ssi_l10n_id_taxform_bukti_potong_pph_f113308/models/bukti_potong_pph_f113308_out_line.py
odoo/addons/ssi_l10n_id_taxform_bukti_potong_pph_f113308/security/ir.model.access.csv
odoo/addons/ssi_l10n_id_taxform_bukti_potong_pph_f113308/security/ir_module_category_data.xml
odoo/addons/ssi_l10n_id_taxform_bukti_potong_pph_f113308/security/ir_rule_data.xml
odoo/addons/ssi_l10n_id_taxform_bukti_potong_pph_f113308/security/res_group_data.xml
odoo/addons/ssi_l10n_id_taxform_bukti_potong_pph_f113308/static/description/icon.png
odoo14_addon_ssi_l10n_id_taxform_bukti_potong_pph_f113308-14.0.1.5.0.dist-info/METADATA
odoo14_addon_ssi_l10n_id_taxform_bukti_potong_pph_f113308-14.0.1.5.0.dist-info/WHEEL
odoo14_addon_ssi_l10n_id_taxform_bukti_potong_pph_f113308-14.0.1.5.0.dist-info/top_level.txt
odoo14_addon_ssi_l10n_id_taxform_bukti_potong_pph_f113308-14.0.1.5.0.dist-info/RECORD
